hyrex/__init__.py
hyrex/__main__.py
hyrex/cli.py
hyrex/configs.py
hyrex/constants.py
hyrex/durable_run.py
hyrex/env_vars.py
hyrex/hyrex_app.py
hyrex/hyrex_cache.py
hyrex/hyrex_context.py
hyrex/hyrex_init.py
hyrex/hyrex_kv.py
hyrex/hyrex_queue.py
hyrex/hyrex_registry.py
hyrex/hyrex_studio_server.py
hyrex/init_db.py
hyrex/logging.py
hyrex/schemas.py
hyrex/task_wrapper.py
hyrex/dispatcher/__init__.py
hyrex/dispatcher/dispatcher.py
hyrex/dispatcher/dispatcher_provider.py
hyrex/dispatcher/performance_dispatcher.py
hyrex/dispatcher/sqlc_dispatcher.py
hyrex/dispatcher/sqlc/_01_create_executor_table.py
hyrex/dispatcher/sqlc/_02_create_hyrex_app_table.py
hyrex/dispatcher/sqlc/_03_create_hyrex_cron_job_table.py
hyrex/dispatcher/sqlc/_04_create_hyrex_scheduler_lock_table.py
hyrex/dispatcher/sqlc/_05_create_hyrex_stats_task_status_counts_table.py
hyrex/dispatcher/sqlc/_06_create_hyrex_stats_task_status_counts_table_indexes.py
hyrex/dispatcher/sqlc/_07_create_hyrex_task_def_table.py
hyrex/dispatcher/sqlc/_08_create_workflow_table.py
hyrex/dispatcher/sqlc/_09_create_system_log_table.py
hyrex/dispatcher/sqlc/_10_create_workflow_run_table.py
hyrex/dispatcher/sqlc/_11_create_hyrex_cron_job_run_details_table.py
hyrex/dispatcher/sqlc/_12_create_hyrex_task_run_table.py
hyrex/dispatcher/sqlc/_13_create_hyrex_task_run_table_indexes.py
hyrex/dispatcher/sqlc/_14_create_results_table.py
hyrex/dispatcher/sqlc/_15_create_hyrex_kv_table.py
hyrex/dispatcher/sqlc/_16_create_hype_cron_job_table.py
hyrex/dispatcher/sqlc/_17_create_hype_cron_job_run_details_table.py
hyrex/dispatcher/sqlc/__init__.py
hyrex/dispatcher/sqlc/acquire_scheduler_lock.py
hyrex/dispatcher/sqlc/advance_stuck_workflows.py
hyrex/dispatcher/sqlc/advance_workflow_run_func.py
hyrex/dispatcher/sqlc/aggregate_dequeue_latency_by_minute.py
hyrex/dispatcher/sqlc/aggregate_dequeue_latency_by_minute_with_lookback.py
hyrex/dispatcher/sqlc/batch_update_heartbeat_log.py
hyrex/dispatcher/sqlc/batch_update_heartbeat_on_executors.py
hyrex-0.10.23.dist-info/licenses/LICENSE
hyrex-0.10.23.dist-info/METADATA
hyrex-0.10.23.dist-info/WHEEL
hyrex-0.10.23.dist-info/entry_points.txt
hyrex-0.10.23.dist-info/top_level.txt
hyrex-0.10.23.dist-info/RECORD
