Metadata-Version: 2.4
Name: hyrex
Version: 0.10.23
Summary: Hyrex is the open-source COLD task orchestration framework built on Postgres.
Author-email: Trevor Reed <trevor@hyrex.io>, Mark Dawson <mark@hyrex.io>
License-Expression: Apache-2.0
Project-URL: Homepage, https://github.com/hyrex-labs/hyrex-python
Project-URL: Source Code, https://github.com/hyrex-labs/hyrex-python
Keywords: hyrex,task,queue,async
Classifier: Programming Language :: Python :: 3
Classifier: Operating System :: OS Independent
Requires-Python: >=3.11
License-File: LICENSE
Requires-Dist: annotated-types>=0.7.0
Requires-Dist: asyncpg>=0.30.0
Requires-Dist: click==8.1.7
Requires-Dist: colorama>=0.4.6
Requires-Dist: croniter>=6.0.0
Requires-Dist: boto3>=1.35.98
Requires-Dist: grpcio>=1.71.0
Requires-Dist: protobuf<6.0.0,>=5.29.5
Requires-Dist: psycopg[binary,pool]>=3.2.1
Requires-Dist: pydantic>=2.8.2
Requires-Dist: pydantic_core>=2.20.1
Requires-Dist: python-dotenv>=1.0.0
Requires-Dist: SQLAlchemy>=2.0.31
Requires-Dist: sqlmodel>=0.0.21
Requires-Dist: tenacity>=9.1.2
Requires-Dist: typer==0.15.3
Requires-Dist: typing_extensions>=4.12.2
Requires-Dist: uuid6==2024.7.10
Provides-Extra: dev
Requires-Dist: black>=22.3.0; extra == "dev"
Dynamic: license-file
